nimic/.DS_Store
nimic/__init__.py
nimic/transpiler.py
nimic-0.0.1.dist-info/WHEEL
nimic-0.0.1.dist-info/entry_points.txt
nimic-0.0.1.dist-info/METADATA
nimic-0.0.1.dist-info/RECORD
