Metadata-Version: 2.4
Name: nimic
Version: 0.0.1
Summary: Pure Python module that facilitates writing AOT compilable code
Author: Dmytro Makogon
License-Expression: MIT
Classifier: Topic :: Software Development :: Compilers
Classifier: Programming Language :: Python :: 3
Requires-Python: >=3.12
Project-URL: Source, https://github.com/dima-quant/nimic.git
